{"_type":"export","__export_format":4,"__export_date":"2020-05-13T19:48:54.523Z","__export_source":"insomnia.desktop.app:v7.1.1","resources":[{"_id":"req_590b795cc24f4fcc8b6c02b5a9121ce6","authentication":{},"body":{},"created":1589205391493,"description":"","headers":[],"isPrivate":false,"metaSortKey":-1589205391493,"method":"GET","modified":1589207688029,"name":"GET Produto","parameters":[],"parentId":"wrk_71ec8ec25b7e49918dcbb56ef526f3ec","settingDisableRenderRequestBody":false,"settingEncodeUrl":true,"settingFollowRedirects":"global","settingRebuildPath":true,"settingSendCookies":true,"settingStoreCookies":true,"url":"localhost:8080/produto","_type":"request"},{"_id":"wrk_71ec8ec25b7e49918dcbb56ef526f3ec","created":1589204182275,"description":"","modified":1589204182275,"name":"Alura Persistência Android","parentId":null,"_type":"workspace"},{"_id":"req_089f92bc85944af4b979d3a818c86f8c","authentication":{},"body":{},"created":1589204403155,"description":"","headers":[],"isPrivate":false,"metaSortKey":-1589204403155,"method":"GET","modified":1589205413463,"name":"GET TEST","parameters":[],"parentId":"wrk_71ec8ec25b7e49918dcbb56ef526f3ec","settingDisableRenderRequestBody":false,"settingEncodeUrl":true,"settingFollowRedirects":"global","settingRebuildPath":true,"settingSendCookies":true,"settingStoreCookies":true,"url":"localhost:8080","_type":"request"},{"_id":"req_ae308e69079d42ba9bf4c56c1d5fd86c","authentication":{},"body":{"mimeType":"application/json","text":"{\n\t\"nome\": \"Chuteira de Futsal\",\n\t\"preco\": \"149.99\",\n\t\"quantidade\":\"21\"\n}"},"created":1589205461118,"description":"","headers":[{"description":"","id":"pair_c0090aae4b0a4692a16ada2b3c80940c","name":"Content-Type","value":"application/json"}],"isPrivate":false,"metaSortKey":-1587348657737,"method":"POST","modified":1589207698914,"name":"POST Produto","parameters":[],"parentId":"wrk_71ec8ec25b7e49918dcbb56ef526f3ec","settingDisableRenderRequestBody":false,"settingEncodeUrl":true,"settingFollowRedirects":"global","settingRebuildPath":true,"settingSendCookies":true,"settingStoreCookies":true,"url":"localhost:8080/produto","_type":"request"},{"_id":"req_0fab165925e041cc86fff9948e3ba207","authentication":{},"body":{"mimeType":"application/json","text":"{\n\t\"nome\": \"Bola de Basquete\",\n\t\"preco\": \"129.99\",\n\t\"quantidade\":\"9\"\n}"},"created":1589205793106,"description":"","headers":[{"description":"","id":"pair_c0090aae4b0a4692a16ada2b3c80940c","name":"Content-Type","value":"application/json"}],"isPrivate":false,"metaSortKey":-1586420785028,"method":"PUT","modified":1589205941304,"name":"UPDATE Produto","parameters":[],"parentId":"wrk_71ec8ec25b7e49918dcbb56ef526f3ec","settingDisableRenderRequestBody":false,"settingEncodeUrl":true,"settingFollowRedirects":"global","settingRebuildPath":true,"settingSendCookies":true,"settingStoreCookies":true,"url":"localhost:8080/produto/1","_type":"request"},{"_id":"req_17e88eae36c248a788f51ab25bf1d372","authentication":{},"body":{"mimeType":"application/json","text":""},"created":1589205888832,"description":"","headers":[{"description":"","id":"pair_c0090aae4b0a4692a16ada2b3c80940c","name":"Content-Type","value":"application/json"}],"isPrivate":false,"metaSortKey":-1585956848673.5,"method":"DELETE","modified":1589205943402,"name":"DELETE Produto","parameters":[],"parentId":"wrk_71ec8ec25b7e49918dcbb56ef526f3ec","settingDisableRenderRequestBody":false,"settingEncodeUrl":true,"settingFollowRedirects":"global","settingRebuildPath":true,"settingSendCookies":true,"settingStoreCookies":true,"url":"localhost:8080/produto/1","_type":"request"},{"_id":"env_51c17cb84928ee0eaa62ee4158cc99e9f96d0a76","color":null,"created":1589204182330,"data":{},"dataPropertyOrder":null,"isPrivate":false,"metaSortKey":1589204182330,"modified":1589204182330,"name":"Base Environment","parentId":"wrk_71ec8ec25b7e49918dcbb56ef526f3ec","_type":"environment"},{"_id":"jar_51c17cb84928ee0eaa62ee4158cc99e9f96d0a76","cookies":[],"created":1589204182333,"modified":1589204182333,"name":"Default Jar","parentId":"wrk_71ec8ec25b7e49918dcbb56ef526f3ec","_type":"cookie_jar"}]}